[{"ID":"Posture constraint","GeometryConstraint":{"ParentObjectID":"","ParentToConstraint":{"ID":"","Position":{"X":0,"Y":0,"Z":0},"Rotation":{"X":0,"Y":0,"Z":0,"W":0},"Parent":"","__isset":{"Parent":false}},"TranslationConstraint":{"Type":"BOX","Limits":{"X":{"Min":0,"Max":0},"Y":{"Min":0,"Max":0},"Z":{"Min":0,"Max":0}}},"RotationConstraint":{"Limits":{"X":{"Min":0,"Max":0},"Y":{"Min":0,"Max":0},"Z":{"Min":0,"Max":0}}},"WeightingFactor":0,"__isset":{"ParentToConstraint":false,"TranslationConstraint":false,"RotationConstraint":false,"WeightingFactor":false}},"VelocityConstraint":{"ParentObjectID":"","ParentToConstraint":{"ID":"","Position":{"X":0,"Y":0,"Z":0},"Rotation":{"X":0,"Y":0,"Z":0,"W":0},"Parent":"","__isset":{"Parent":false}},"TranslationalVelocity":{"X":0,"Y":0,"Z":0},"RotationalVelocity":{"X":0,"Y":0,"Z":0},"WeightingFactor":0,"__isset":{"ParentToConstraint":false,"TranslationalVelocity":false,"RotationalVelocity":false,"WeightingFactor":false}},"AccelerationConstraint":{"ParentObjectID":"","ParentToConstraint":{"ID":"","Position":{"X":0,"Y":0,"Z":0},"Rotation":{"X":0,"Y":0,"Z":0,"W":0},"Parent":"","__isset":{"Parent":false}},"TranslationalAcceleration":{"X":0,"Y":0,"Z":0},"RotationalAcceleration":{"X":0,"Y":0,"Z":0},"WeightingFactor":0,"__isset":{"ParentToConstraint":false,"TranslationalAcceleration":false,"RotationalAcceleration":false,"WeightingFactor":false}},"PathConstraint":{"PolygonPoints":[],"WeightingFactor":0,"__isset":{"WeightingFactor":false}},"JointPathConstraint":{"JointType":"Undefined","PathConstraint":{"PolygonPoints":[],"WeightingFactor":0,"__isset":{"WeightingFactor":false}}},"PostureConstraint":{"Posture":{"AvatarID":"","PostureData":[],"PartialJointList":[],"__isset":{"PartialJointList":false}},"JointConstraints":[{"JointType":"RightWrist","GeometryConstraint":{"ParentObjectID":"","ParentToConstraint":{"ID":"458afc95-84a4-4123-b945-6b72030559e5","Position":{"X":0.06809999793767929,"Y":0.9466000199317932,"Z":0.5289999842643738},"Rotation":{"X":0.0877721756696701,"Y":-0.7122747898101807,"Z":-0.695723295211792,"W":-0.030495429411530495},"Parent":"","__isset":{"Parent":false}},"TranslationConstraint":{"Type":"BOX","Limits":{"X":{"Min":0,"Max":0},"Y":{"Min":0,"Max":0},"Z":{"Min":0,"Max":0}}},"RotationConstraint":{"Limits":{"X":{"Min":0,"Max":0},"Y":{"Min":0,"Max":0},"Z":{"Min":0,"Max":0}}},"WeightingFactor":0,"__isset":{"ParentToConstraint":true,"TranslationConstraint":false,"RotationConstraint":false,"WeightingFactor":false}},"VelocityConstraint":{"ParentObjectID":"","ParentToConstraint":{"ID":"","Position":{"X":0,"Y":0,"Z":0},"Rotation":{"X":0,"Y":0,"Z":0,"W":0},"Parent":"","__isset":{"Parent":false}},"TranslationalVelocity":{"X":0,"Y":0,"Z":0},"RotationalVelocity":{"X":0,"Y":0,"Z":0},"WeightingFactor":0,"__isset":{"ParentToConstraint":false,"TranslationalVelocity":false,"RotationalVelocity":false,"WeightingFactor":false}},"AccelerationConstraint":{"ParentObjectID":"","ParentToConstraint":{"ID":"","Position":{"X":0,"Y":0,"Z":0},"Rotation":{"X":0,"Y":0,"Z":0,"W":0},"Parent":"","__isset":{"Parent":false}},"TranslationalAcceleration":{"X":0,"Y":0,"Z":0},"RotationalAcceleration":{"X":0,"Y":0,"Z":0},"WeightingFactor":0,"__isset":{"ParentToConstraint":false,"TranslationalAcceleration":false,"RotationalAcceleration":false,"WeightingFactor":false}},"__isset":{"GeometryConstraint":true,"VelocityConstraint":false,"AccelerationConstraint":false}},{"JointType":"RightMiddleProximal","GeometryConstraint":{"ParentObjectID":"","ParentToConstraint":{"ID":"a8a9b45c-78a9-497d-a1a3-a679b5c9fcd0","Position":{"X":-1.1920928955078125E-7,"Y":0.11821141839027405,"Z":5.960468740795477E-8},"Rotation":{"X":3.7252898543727042E-9,"Y":4.738102887813511E-8,"Z":-0.32847949862480164,"W":0.9445111751556396},"Parent":"","__isset":{"Parent":false}},"TranslationConstraint":{"Type":"BOX","Limits":{"X":{"Min":0,"Max":0},"Y":{"Min":0,"Max":0},"Z":{"Min":0,"Max":0}}},"RotationConstraint":{"Limits":{"X":{"Min":0,"Max":0},"Y":{"Min":0,"Max":0},"Z":{"Min":0,"Max":0}}},"WeightingFactor":0,"__isset":{"ParentToConstraint":true,"TranslationConstraint":false,"RotationConstraint":false,"WeightingFactor":false}},"VelocityConstraint":{"ParentObjectID":"","ParentToConstraint":{"ID":"","Position":{"X":0,"Y":0,"Z":0},"Rotation":{"X":0,"Y":0,"Z":0,"W":0},"Parent":"","__isset":{"Parent":false}},"TranslationalVelocity":{"X":0,"Y":0,"Z":0},"RotationalVelocity":{"X":0,"Y":0,"Z":0},"WeightingFactor":0,"__isset":{"ParentToConstraint":false,"TranslationalVelocity":false,"RotationalVelocity":false,"WeightingFactor":false}},"AccelerationConstraint":{"ParentObjectID":"","ParentToConstraint":{"ID":"","Position":{"X":0,"Y":0,"Z":0},"Rotation":{"X":0,"Y":0,"Z":0,"W":0},"Parent":"","__isset":{"Parent":false}},"TranslationalAcceleration":{"X":0,"Y":0,"Z":0},"RotationalAcceleration":{"X":0,"Y":0,"Z":0},"WeightingFactor":0,"__isset":{"ParentToConstraint":false,"TranslationalAcceleration":false,"RotationalAcceleration":false,"WeightingFactor":false}},"__isset":{"GeometryConstraint":true,"VelocityConstraint":false,"AccelerationConstraint":false}},{"JointType":"RightMiddleMeta","GeometryConstraint":{"ParentObjectID":"","ParentToConstraint":{"ID":"cbbc0188-4cba-4a7c-b2f7-d090a7ce5779","Position":{"X":0,"Y":0.03957550227642059,"Z":0},"Rotation":{"X":-2.5678856374611314E-8,"Y":2.5543320347765075E-8,"Z":-0.36731332540512085,"W":0.9300972819328308},"Parent":"","__isset":{"Parent":false}},"TranslationConstraint":{"Type":"BOX","Limits":{"X":{"Min":0,"Max":0},"Y":{"Min":0,"Max":0},"Z":{"Min":0,"Max":0}}},"RotationConstraint":{"Limits":{"X":{"Min":0,"Max":0},"Y":{"Min":0,"Max":0},"Z":{"Min":0,"Max":0}}},"WeightingFactor":0,"__isset":{"ParentToConstraint":true,"TranslationConstraint":false,"RotationConstraint":false,"WeightingFactor":false}},"VelocityConstraint":{"ParentObjectID":"","ParentToConstraint":{"ID":"","Position":{"X":0,"Y":0,"Z":0},"Rotation":{"X":0,"Y":0,"Z":0,"W":0},"Parent":"","__isset":{"Parent":false}},"TranslationalVelocity":{"X":0,"Y":0,"Z":0},"RotationalVelocity":{"X":0,"Y":0,"Z":0},"WeightingFactor":0,"__isset":{"ParentToConstraint":false,"TranslationalVelocity":false,"RotationalVelocity":false,"WeightingFactor":false}},"AccelerationConstraint":{"ParentObjectID":"","ParentToConstraint":{"ID":"","Position":{"X":0,"Y":0,"Z":0},"Rotation":{"X":0,"Y":0,"Z":0,"W":0},"Parent":"","__isset":{"Parent":false}},"TranslationalAcceleration":{"X":0,"Y":0,"Z":0},"RotationalAcceleration":{"X":0,"Y":0,"Z":0},"WeightingFactor":0,"__isset":{"ParentToConstraint":false,"TranslationalAcceleration":false,"RotationalAcceleration":false,"WeightingFactor":false}},"__isset":{"GeometryConstraint":true,"VelocityConstraint":false,"AccelerationConstraint":false}},{"JointType":"RightMiddleDistal","GeometryConstraint":{"ParentObjectID":"","ParentToConstraint":{"ID":"4e5d24c9-57b6-4bb3-a8fe-9b4c628edb47","Position":{"X":0,"Y":0.031451690942049026,"Z":0},"Rotation":{"X":0,"Y":0,"Z":0,"W":1},"Parent":"","__isset":{"Parent":false}},"TranslationConstraint":{"Type":"BOX","Limits":{"X":{"Min":0,"Max":0},"Y":{"Min":0,"Max":0},"Z":{"Min":0,"Max":0}}},"RotationConstraint":{"Limits":{"X":{"Min":0,"Max":0},"Y":{"Min":0,"Max":0},"Z":{"Min":0,"Max":0}}},"WeightingFactor":0,"__isset":{"ParentToConstraint":true,"TranslationConstraint":false,"RotationConstraint":false,"WeightingFactor":false}},"VelocityConstraint":{"ParentObjectID":"","ParentToConstraint":{"ID":"","Position":{"X":0,"Y":0,"Z":0},"Rotation":{"X":0,"Y":0,"Z":0,"W":0},"Parent":"","__isset":{"Parent":false}},"TranslationalVelocity":{"X":0,"Y":0,"Z":0},"RotationalVelocity":{"X":0,"Y":0,"Z":0},"WeightingFactor":0,"__isset":{"ParentToConstraint":false,"TranslationalVelocity":false,"RotationalVelocity":false,"WeightingFactor":false}},"AccelerationConstraint":{"ParentObjectID":"","ParentToConstraint":{"ID":"","Position":{"X":0,"Y":0,"Z":0},"Rotation":{"X":0,"Y":0,"Z":0,"W":0},"Parent":"","__isset":{"Parent":false}},"TranslationalAcceleration":{"X":0,"Y":0,"Z":0},"RotationalAcceleration":{"X":0,"Y":0,"Z":0},"WeightingFactor":0,"__isset":{"ParentToConstraint":false,"TranslationalAcceleration":false,"RotationalAcceleration":false,"WeightingFactor":false}},"__isset":{"GeometryConstraint":true,"VelocityConstraint":false,"AccelerationConstraint":false}},{"JointType":"RightMiddleTip","GeometryConstraint":{"ParentObjectID":"","ParentToConstraint":{"ID":"d8fc72c8-aba8-4ca2-bf4e-77421c84a0a8","Position":{"X":0,"Y":0.029999999329447746,"Z":0},"Rotation":{"X":0,"Y":0,"Z":0,"W":1},"Parent":"","__isset":{"Parent":false}},"TranslationConstraint":{"Type":"BOX","Limits":{"X":{"Min":0,"Max":0},"Y":{"Min":0,"Max":0},"Z":{"Min":0,"Max":0}}},"RotationConstraint":{"Limits":{"X":{"Min":0,"Max":0},"Y":{"Min":0,"Max":0},"Z":{"Min":0,"Max":0}}},"WeightingFactor":0,"__isset":{"ParentToConstraint":true,"TranslationConstraint":false,"RotationConstraint":false,"WeightingFactor":false}},"VelocityConstraint":{"ParentObjectID":"","ParentToConstraint":{"ID":"","Position":{"X":0,"Y":0,"Z":0},"Rotation":{"X":0,"Y":0,"Z":0,"W":0},"Parent":"","__isset":{"Parent":false}},"TranslationalVelocity":{"X":0,"Y":0,"Z":0},"RotationalVelocity":{"X":0,"Y":0,"Z":0},"WeightingFactor":0,"__isset":{"ParentToConstraint":false,"TranslationalVelocity":false,"RotationalVelocity":false,"WeightingFactor":false}},"AccelerationConstraint":{"ParentObjectID":"","ParentToConstraint":{"ID":"","Position":{"X":0,"Y":0,"Z":0},"Rotation":{"X":0,"Y":0,"Z":0,"W":0},"Parent":"","__isset":{"Parent":false}},"TranslationalAcceleration":{"X":0,"Y":0,"Z":0},"RotationalAcceleration":{"X":0,"Y":0,"Z":0},"WeightingFactor":0,"__isset":{"ParentToConstraint":false,"TranslationalAcceleration":false,"RotationalAcceleration":false,"WeightingFactor":false}},"__isset":{"GeometryConstraint":true,"VelocityConstraint":false,"AccelerationConstraint":false}},{"JointType":"RightIndexProximal","GeometryConstraint":{"ParentObjectID":"","ParentToConstraint":{"ID":"f12b3dc5-5029-46bd-97e7-b18c2d828ff2","Position":{"X":-1.1175872316471214E-7,"Y":0.1199701726436615,"Z":0.02809811383485794},"Rotation":{"X":3.7252898543727042E-9,"Y":4.738102887813511E-8,"Z":-0.32847949862480164,"W":0.9445111751556396},"Parent":"","__isset":{"Parent":false}},"TranslationConstraint":{"Type":"BOX","Limits":{"X":{"Min":0,"Max":0},"Y":{"Min":0,"Max":0},"Z":{"Min":0,"Max":0}}},"RotationConstraint":{"Limits":{"X":{"Min":0,"Max":0},"Y":{"Min":0,"Max":0},"Z":{"Min":0,"Max":0}}},"WeightingFactor":0,"__isset":{"ParentToConstraint":true,"TranslationConstraint":false,"RotationConstraint":false,"WeightingFactor":false}},"VelocityConstraint":{"ParentObjectID":"","ParentToConstraint":{"ID":"","Position":{"X":0,"Y":0,"Z":0},"Rotation":{"X":0,"Y":0,"Z":0,"W":0},"Parent":"","__isset":{"Parent":false}},"TranslationalVelocity":{"X":0,"Y":0,"Z":0},"RotationalVelocity":{"X":0,"Y":0,"Z":0},"WeightingFactor":0,"__isset":{"ParentToConstraint":false,"TranslationalVelocity":false,"RotationalVelocity":false,"WeightingFactor":false}},"AccelerationConstraint":{"ParentObjectID":"","ParentToConstraint":{"ID":"","Position":{"X":0,"Y":0,"Z":0},"Rotation":{"X":0,"Y":0,"Z":0,"W":0},"Parent":"","__isset":{"Parent":false}},"TranslationalAcceleration":{"X":0,"Y":0,"Z":0},"RotationalAcceleration":{"X":0,"Y":0,"Z":0},"WeightingFactor":0,"__isset":{"ParentToConstraint":false,"TranslationalAcceleration":false,"RotationalAcceleration":false,"WeightingFactor":false}},"__isset":{"GeometryConstraint":true,"VelocityConstraint":false,"AccelerationConstraint":false}},{"JointType":"RightIndexMeta","GeometryConstraint":{"ParentObjectID":"","ParentToConstraint":{"ID":"73754830-825e-4577-bddf-773df9b86405","Position":{"X":0,"Y":0.030107565224170685,"Z":0},"Rotation":{"X":-2.5678856374611314E-8,"Y":2.5543320347765075E-8,"Z":-0.36731332540512085,"W":0.9300972819328308},"Parent":"","__isset":{"Parent":false}},"TranslationConstraint":{"Type":"BOX","Limits":{"X":{"Min":0,"Max":0},"Y":{"Min":0,"Max":0},"Z":{"Min":0,"Max":0}}},"RotationConstraint":{"Limits":{"X":{"Min":0,"Max":0},"Y":{"Min":0,"Max":0},"Z":{"Min":0,"Max":0}}},"WeightingFactor":0,"__isset":{"ParentToConstraint":true,"TranslationConstraint":false,"RotationConstraint":false,"WeightingFactor":false}},"VelocityConstraint":{"ParentObjectID":"","ParentToConstraint":{"ID":"","Position":{"X":0,"Y":0,"Z":0},"Rotation":{"X":0,"Y":0,"Z":0,"W":0},"Parent":"","__isset":{"Parent":false}},"TranslationalVelocity":{"X":0,"Y":0,"Z":0},"RotationalVelocity":{"X":0,"Y":0,"Z":0},"WeightingFactor":0,"__isset":{"ParentToConstraint":false,"TranslationalVelocity":false,"RotationalVelocity":false,"WeightingFactor":false}},"AccelerationConstraint":{"ParentObjectID":"","ParentToConstraint":{"ID":"","Position":{"X":0,"Y":0,"Z":0},"Rotation":{"X":0,"Y":0,"Z":0,"W":0},"Parent":"","__isset":{"Parent":false}},"TranslationalAcceleration":{"X":0,"Y":0,"Z":0},"RotationalAcceleration":{"X":0,"Y":0,"Z":0},"WeightingFactor":0,"__isset":{"ParentToConstraint":false,"TranslationalAcceleration":false,"RotationalAcceleration":false,"WeightingFactor":false}},"__isset":{"GeometryConstraint":true,"VelocityConstraint":false,"AccelerationConstraint":false}},{"JointType":"RightIndexDistal","GeometryConstraint":{"ParentObjectID":"","ParentToConstraint":{"ID":"18019e95-d4fc-4a61-aa80-85e5bdea64ef","Position":{"X":0,"Y":0.02719544805586338,"Z":0},"Rotation":{"X":0,"Y":0,"Z":0,"W":1},"Parent":"","__isset":{"Parent":false}},"TranslationConstraint":{"Type":"BOX","Limits":{"X":{"Min":0,"Max":0},"Y":{"Min":0,"Max":0},"Z":{"Min":0,"Max":0}}},"RotationConstraint":{"Limits":{"X":{"Min":0,"Max":0},"Y":{"Min":0,"Max":0},"Z":{"Min":0,"Max":0}}},"WeightingFactor":0,"__isset":{"ParentToConstraint":true,"TranslationConstraint":false,"RotationConstraint":false,"WeightingFactor":false}},"VelocityConstraint":{"ParentObjectID":"","ParentToConstraint":{"ID":"","Position":{"X":0,"Y":0,"Z":0},"Rotation":{"X":0,"Y":0,"Z":0,"W":0},"Parent":"","__isset":{"Parent":false}},"TranslationalVelocity":{"X":0,"Y":0,"Z":0},"RotationalVelocity":{"X":0,"Y":0,"Z":0},"WeightingFactor":0,"__isset":{"ParentToConstraint":false,"TranslationalVelocity":false,"RotationalVelocity":false,"WeightingFactor":false}},"AccelerationConstraint":{"ParentObjectID":"","ParentToConstraint":{"ID":"","Position":{"X":0,"Y":0,"Z":0},"Rotation":{"X":0,"Y":0,"Z":0,"W":0},"Parent":"","__isset":{"Parent":false}},"TranslationalAcceleration":{"X":0,"Y":0,"Z":0},"RotationalAcceleration":{"X":0,"Y":0,"Z":0},"WeightingFactor":0,"__isset":{"ParentToConstraint":false,"TranslationalAcceleration":false,"RotationalAcceleration":false,"WeightingFactor":false}},"__isset":{"GeometryConstraint":true,"VelocityConstraint":false,"AccelerationConstraint":false}},{"JointType":"RightIndexTip","GeometryConstraint":{"ParentObjectID":"","ParentToConstraint":{"ID":"fe6d9b54-541e-4e76-9373-d6ac5208b3a5","Position":{"X":0,"Y":0.029999999329447746,"Z":0},"Rotation":{"X":0,"Y":0,"Z":0,"W":1},"Parent":"","__isset":{"Parent":false}},"TranslationConstraint":{"Type":"BOX","Limits":{"X":{"Min":0,"Max":0},"Y":{"Min":0,"Max":0},"Z":{"Min":0,"Max":0}}},"RotationConstraint":{"Limits":{"X":{"Min":0,"Max":0},"Y":{"Min":0,"Max":0},"Z":{"Min":0,"Max":0}}},"WeightingFactor":0,"__isset":{"ParentToConstraint":true,"TranslationConstraint":false,"RotationConstraint":false,"WeightingFactor":false}},"VelocityConstraint":{"ParentObjectID":"","ParentToConstraint":{"ID":"","Position":{"X":0,"Y":0,"Z":0},"Rotation":{"X":0,"Y":0,"Z":0,"W":0},"Parent":"","__isset":{"Parent":false}},"TranslationalVelocity":{"X":0,"Y":0,"Z":0},"RotationalVelocity":{"X":0,"Y":0,"Z":0},"WeightingFactor":0,"__isset":{"ParentToConstraint":false,"TranslationalVelocity":false,"RotationalVelocity":false,"WeightingFactor":false}},"AccelerationConstraint":{"ParentObjectID":"","ParentToConstraint":{"ID":"","Position":{"X":0,"Y":0,"Z":0},"Rotation":{"X":0,"Y":0,"Z":0,"W":0},"Parent":"","__isset":{"Parent":false}},"TranslationalAcceleration":{"X":0,"Y":0,"Z":0},"RotationalAcceleration":{"X":0,"Y":0,"Z":0},"WeightingFactor":0,"__isset":{"ParentToConstraint":false,"TranslationalAcceleration":false,"RotationalAcceleration":false,"WeightingFactor":false}},"__isset":{"GeometryConstraint":true,"VelocityConstraint":false,"AccelerationConstraint":false}},{"JointType":"RightRingProximal","GeometryConstraint":{"ParentObjectID":"","ParentToConstraint":{"ID":"ee8180c7-76a7-4f2f-89b9-f3cdff6cbdc6","Position":{"X":-1.2293459406009788E-7,"Y":0.11081787943840027,"Z":-0.022562745958566666},"Rotation":{"X":3.7252898543727042E-9,"Y":4.738102887813511E-8,"Z":-0.32847949862480164,"W":0.9445111751556396},"Parent":"","__isset":{"Parent":false}},"TranslationConstraint":{"Type":"BOX","Limits":{"X":{"Min":0,"Max":0},"Y":{"Min":0,"Max":0},"Z":{"Min":0,"Max":0}}},"RotationConstraint":{"Limits":{"X":{"Min":0,"Max":0},"Y":{"Min":0,"Max":0},"Z":{"Min":0,"Max":0}}},"WeightingFactor":0,"__isset":{"ParentToConstraint":true,"TranslationConstraint":false,"RotationConstraint":false,"WeightingFactor":false}},"VelocityConstraint":{"ParentObjectID":"","ParentToConstraint":{"ID":"","Position":{"X":0,"Y":0,"Z":0},"Rotation":{"X":0,"Y":0,"Z":0,"W":0},"Parent":"","__isset":{"Parent":false}},"TranslationalVelocity":{"X":0,"Y":0,"Z":0},"RotationalVelocity":{"X":0,"Y":0,"Z":0},"WeightingFactor":0,"__isset":{"ParentToConstraint":false,"TranslationalVelocity":false,"RotationalVelocity":false,"WeightingFactor":false}},"AccelerationConstraint":{"ParentObjectID":"","ParentToConstraint":{"ID":"","Position":{"X":0,"Y":0,"Z":0},"Rotation":{"X":0,"Y":0,"Z":0,"W":0},"Parent":"","__isset":{"Parent":false}},"TranslationalAcceleration":{"X":0,"Y":0,"Z":0},"RotationalAcceleration":{"X":0,"Y":0,"Z":0},"WeightingFactor":0,"__isset":{"ParentToConstraint":false,"TranslationalAcceleration":false,"RotationalAcceleration":false,"WeightingFactor":false}},"__isset":{"GeometryConstraint":true,"VelocityConstraint":false,"AccelerationConstraint":false}},{"JointType":"RightRingMeta","GeometryConstraint":{"ParentObjectID":"","ParentToConstraint":{"ID":"c02a8024-3d6a-4de5-8d9b-9b717f618437","Position":{"X":0,"Y":0.03474121913313866,"Z":0},"Rotation":{"X":-2.5678856374611314E-8,"Y":2.5543320347765075E-8,"Z":-0.36731332540512085,"W":0.9300972819328308},"Parent":"","__isset":{"Parent":false}},"TranslationConstraint":{"Type":"BOX","Limits":{"X":{"Min":0,"Max":0},"Y":{"Min":0,"Max":0},"Z":{"Min":0,"Max":0}}},"RotationConstraint":{"Limits":{"X":{"Min":0,"Max":0},"Y":{"Min":0,"Max":0},"Z":{"Min":0,"Max":0}}},"WeightingFactor":0,"__isset":{"ParentToConstraint":true,"TranslationConstraint":false,"RotationConstraint":false,"WeightingFactor":false}},"VelocityConstraint":{"ParentObjectID":"","ParentToConstraint":{"ID":"","Position":{"X":0,"Y":0,"Z":0},"Rotation":{"X":0,"Y":0,"Z":0,"W":0},"Parent":"","__isset":{"Parent":false}},"TranslationalVelocity":{"X":0,"Y":0,"Z":0},"RotationalVelocity":{"X":0,"Y":0,"Z":0},"WeightingFactor":0,"__isset":{"ParentToConstraint":false,"TranslationalVelocity":false,"RotationalVelocity":false,"WeightingFactor":false}},"AccelerationConstraint":{"ParentObjectID":"","ParentToConstraint":{"ID":"","Position":{"X":0,"Y":0,"Z":0},"Rotation":{"X":0,"Y":0,"Z":0,"W":0},"Parent":"","__isset":{"Parent":false}},"TranslationalAcceleration":{"X":0,"Y":0,"Z":0},"RotationalAcceleration":{"X":0,"Y":0,"Z":0},"WeightingFactor":0,"__isset":{"ParentToConstraint":false,"TranslationalAcceleration":false,"RotationalAcceleration":false,"WeightingFactor":false}},"__isset":{"GeometryConstraint":true,"VelocityConstraint":false,"AccelerationConstraint":false}},{"JointType":"RightRingDistal","GeometryConstraint":{"ParentObjectID":"","ParentToConstraint":{"ID":"aa7d5a81-5713-4bb3-8a14-af63e911b2c1","Position":{"X":0,"Y":0.02874886617064476,"Z":0},"Rotation":{"X":0,"Y":0,"Z":0,"W":1},"Parent":"","__isset":{"Parent":false}},"TranslationConstraint":{"Type":"BOX","Limits":{"X":{"Min":0,"Max":0},"Y":{"Min":0,"Max":0},"Z":{"Min":0,"Max":0}}},"RotationConstraint":{"Limits":{"X":{"Min":0,"Max":0},"Y":{"Min":0,"Max":0},"Z":{"Min":0,"Max":0}}},"WeightingFactor":0,"__isset":{"ParentToConstraint":true,"TranslationConstraint":false,"RotationConstraint":false,"WeightingFactor":false}},"VelocityConstraint":{"ParentObjectID":"","ParentToConstraint":{"ID":"","Position":{"X":0,"Y":0,"Z":0},"Rotation":{"X":0,"Y":0,"Z":0,"W":0},"Parent":"","__isset":{"Parent":false}},"TranslationalVelocity":{"X":0,"Y":0,"Z":0},"RotationalVelocity":{"X":0,"Y":0,"Z":0},"WeightingFactor":0,"__isset":{"ParentToConstraint":false,"TranslationalVelocity":false,"RotationalVelocity":false,"WeightingFactor":false}},"AccelerationConstraint":{"ParentObjectID":"","ParentToConstraint":{"ID":"","Position":{"X":0,"Y":0,"Z":0},"Rotation":{"X":0,"Y":0,"Z":0,"W":0},"Parent":"","__isset":{"Parent":false}},"TranslationalAcceleration":{"X":0,"Y":0,"Z":0},"RotationalAcceleration":{"X":0,"Y":0,"Z":0},"WeightingFactor":0,"__isset":{"ParentToConstraint":false,"TranslationalAcceleration":false,"RotationalAcceleration":false,"WeightingFactor":false}},"__isset":{"GeometryConstraint":true,"VelocityConstraint":false,"AccelerationConstraint":false}},{"JointType":"RightRingTip","GeometryConstraint":{"ParentObjectID":"","ParentToConstraint":{"ID":"d6f6f5a4-b173-4256-83d1-0872446dc73e","Position":{"X":0,"Y":0.029999999329447746,"Z":0},"Rotation":{"X":0,"Y":0,"Z":0,"W":1},"Parent":"","__isset":{"Parent":false}},"TranslationConstraint":{"Type":"BOX","Limits":{"X":{"Min":0,"Max":0},"Y":{"Min":0,"Max":0},"Z":{"Min":0,"Max":0}}},"RotationConstraint":{"Limits":{"X":{"Min":0,"Max":0},"Y":{"Min":0,"Max":0},"Z":{"Min":0,"Max":0}}},"WeightingFactor":0,"__isset":{"ParentToConstraint":true,"TranslationConstraint":false,"RotationConstraint":false,"WeightingFactor":false}},"VelocityConstraint":{"ParentObjectID":"","ParentToConstraint":{"ID":"","Position":{"X":0,"Y":0,"Z":0},"Rotation":{"X":0,"Y":0,"Z":0,"W":0},"Parent":"","__isset":{"Parent":false}},"TranslationalVelocity":{"X":0,"Y":0,"Z":0},"RotationalVelocity":{"X":0,"Y":0,"Z":0},"WeightingFactor":0,"__isset":{"ParentToConstraint":false,"TranslationalVelocity":false,"RotationalVelocity":false,"WeightingFactor":false}},"AccelerationConstraint":{"ParentObjectID":"","ParentToConstraint":{"ID":"","Position":{"X":0,"Y":0,"Z":0},"Rotation":{"X":0,"Y":0,"Z":0,"W":0},"Parent":"","__isset":{"Parent":false}},"TranslationalAcceleration":{"X":0,"Y":0,"Z":0},"RotationalAcceleration":{"X":0,"Y":0,"Z":0},"WeightingFactor":0,"__isset":{"ParentToConstraint":false,"TranslationalAcceleration":false,"RotationalAcceleration":false,"WeightingFactor":false}},"__isset":{"GeometryConstraint":true,"VelocityConstraint":false,"AccelerationConstraint":false}},{"JointType":"RightLittleProximal","GeometryConstraint":{"ParentObjectID":"","ParentToConstraint":{"ID":"092b06a4-aab6-4502-8997-4e3db2978a6c","Position":{"X":-1.266598843585598E-7,"Y":0.10160025954246521,"Z":-0.041280217468738556},"Rotation":{"X":3.7252898543727042E-9,"Y":4.738102887813511E-8,"Z":-0.32847949862480164,"W":0.9445111751556396},"Parent":"","__isset":{"Parent":false}},"TranslationConstraint":{"Type":"BOX","Limits":{"X":{"Min":0,"Max":0},"Y":{"Min":0,"Max":0},"Z":{"Min":0,"Max":0}}},"RotationConstraint":{"Limits":{"X":{"Min":0,"Max":0},"Y":{"Min":0,"Max":0},"Z":{"Min":0,"Max":0}}},"WeightingFactor":0,"__isset":{"ParentToConstraint":true,"TranslationConstraint":false,"RotationConstraint":false,"WeightingFactor":false}},"VelocityConstraint":{"ParentObjectID":"","ParentToConstraint":{"ID":"","Position":{"X":0,"Y":0,"Z":0},"Rotation":{"X":0,"Y":0,"Z":0,"W":0},"Parent":"","__isset":{"Parent":false}},"TranslationalVelocity":{"X":0,"Y":0,"Z":0},"RotationalVelocity":{"X":0,"Y":0,"Z":0},"WeightingFactor":0,"__isset":{"ParentToConstraint":false,"TranslationalVelocity":false,"RotationalVelocity":false,"WeightingFactor":false}},"AccelerationConstraint":{"ParentObjectID":"","ParentToConstraint":{"ID":"","Position":{"X":0,"Y":0,"Z":0},"Rotation":{"X":0,"Y":0,"Z":0,"W":0},"Parent":"","__isset":{"Parent":false}},"TranslationalAcceleration":{"X":0,"Y":0,"Z":0},"RotationalAcceleration":{"X":0,"Y":0,"Z":0},"WeightingFactor":0,"__isset":{"ParentToConstraint":false,"TranslationalAcceleration":false,"RotationalAcceleration":false,"WeightingFactor":false}},"__isset":{"GeometryConstraint":true,"VelocityConstraint":false,"AccelerationConstraint":false}},{"JointType":"RightLittleMeta","GeometryConstraint":{"ParentObjectID":"","ParentToConstraint":{"ID":"3f9dbb46-58eb-4687-8b53-50bf409f95fd","Position":{"X":0,"Y":0.02462206967175007,"Z":0},"Rotation":{"X":-2.5678856374611314E-8,"Y":2.5543320347765075E-8,"Z":-0.36731332540512085,"W":0.9300972819328308},"Parent":"","__isset":{"Parent":false}},"TranslationConstraint":{"Type":"BOX","Limits":{"X":{"Min":0,"Max":0},"Y":{"Min":0,"Max":0},"Z":{"Min":0,"Max":0}}},"RotationConstraint":{"Limits":{"X":{"Min":0,"Max":0},"Y":{"Min":0,"Max":0},"Z":{"Min":0,"Max":0}}},"WeightingFactor":0,"__isset":{"ParentToConstraint":true,"TranslationConstraint":false,"RotationConstraint":false,"WeightingFactor":false}},"VelocityConstraint":{"ParentObjectID":"","ParentToConstraint":{"ID":"","Position":{"X":0,"Y":0,"Z":0},"Rotation":{"X":0,"Y":0,"Z":0,"W":0},"Parent":"","__isset":{"Parent":false}},"TranslationalVelocity":{"X":0,"Y":0,"Z":0},"RotationalVelocity":{"X":0,"Y":0,"Z":0},"WeightingFactor":0,"__isset":{"ParentToConstraint":false,"TranslationalVelocity":false,"RotationalVelocity":false,"WeightingFactor":false}},"AccelerationConstraint":{"ParentObjectID":"","ParentToConstraint":{"ID":"","Position":{"X":0,"Y":0,"Z":0},"Rotation":{"X":0,"Y":0,"Z":0,"W":0},"Parent":"","__isset":{"Parent":false}},"TranslationalAcceleration":{"X":0,"Y":0,"Z":0},"RotationalAcceleration":{"X":0,"Y":0,"Z":0},"WeightingFactor":0,"__isset":{"ParentToConstraint":false,"TranslationalAcceleration":false,"RotationalAcceleration":false,"WeightingFactor":false}},"__isset":{"GeometryConstraint":true,"VelocityConstraint":false,"AccelerationConstraint":false}},{"JointType":"RightLittleDistal","GeometryConstraint":{"ParentObjectID":"","ParentToConstraint":{"ID":"3d9d4899-09ea-4752-94f1-e706105661a6","Position":{"X":0,"Y":0.018097683787345886,"Z":0},"Rotation":{"X":0,"Y":0,"Z":0,"W":1},"Parent":"","__isset":{"Parent":false}},"TranslationConstraint":{"Type":"BOX","Limits":{"X":{"Min":0,"Max":0},"Y":{"Min":0,"Max":0},"Z":{"Min":0,"Max":0}}},"RotationConstraint":{"Limits":{"X":{"Min":0,"Max":0},"Y":{"Min":0,"Max":0},"Z":{"Min":0,"Max":0}}},"WeightingFactor":0,"__isset":{"ParentToConstraint":true,"TranslationConstraint":false,"RotationConstraint":false,"WeightingFactor":false}},"VelocityConstraint":{"ParentObjectID":"","ParentToConstraint":{"ID":"","Position":{"X":0,"Y":0,"Z":0},"Rotation":{"X":0,"Y":0,"Z":0,"W":0},"Parent":"","__isset":{"Parent":false}},"TranslationalVelocity":{"X":0,"Y":0,"Z":0},"RotationalVelocity":{"X":0,"Y":0,"Z":0},"WeightingFactor":0,"__isset":{"ParentToConstraint":false,"TranslationalVelocity":false,"RotationalVelocity":false,"WeightingFactor":false}},"AccelerationConstraint":{"ParentObjectID":"","ParentToConstraint":{"ID":"","Position":{"X":0,"Y":0,"Z":0},"Rotation":{"X":0,"Y":0,"Z":0,"W":0},"Parent":"","__isset":{"Parent":false}},"TranslationalAcceleration":{"X":0,"Y":0,"Z":0},"RotationalAcceleration":{"X":0,"Y":0,"Z":0},"WeightingFactor":0,"__isset":{"ParentToConstraint":false,"TranslationalAcceleration":false,"RotationalAcceleration":false,"WeightingFactor":false}},"__isset":{"GeometryConstraint":true,"VelocityConstraint":false,"AccelerationConstraint":false}},{"JointType":"RightLittleTip","GeometryConstraint":{"ParentObjectID":"","ParentToConstraint":{"ID":"5b0a735a-f65f-414c-868c-3703a7ec285e","Position":{"X":0,"Y":0.029999999329447746,"Z":0},"Rotation":{"X":0,"Y":0,"Z":0,"W":1},"Parent":"","__isset":{"Parent":false}},"TranslationConstraint":{"Type":"BOX","Limits":{"X":{"Min":0,"Max":0},"Y":{"Min":0,"Max":0},"Z":{"Min":0,"Max":0}}},"RotationConstraint":{"Limits":{"X":{"Min":0,"Max":0},"Y":{"Min":0,"Max":0},"Z":{"Min":0,"Max":0}}},"WeightingFactor":0,"__isset":{"ParentToConstraint":true,"TranslationConstraint":false,"RotationConstraint":false,"WeightingFactor":false}},"VelocityConstraint":{"ParentObjectID":"","ParentToConstraint":{"ID":"","Position":{"X":0,"Y":0,"Z":0},"Rotation":{"X":0,"Y":0,"Z":0,"W":0},"Parent":"","__isset":{"Parent":false}},"TranslationalVelocity":{"X":0,"Y":0,"Z":0},"RotationalVelocity":{"X":0,"Y":0,"Z":0},"WeightingFactor":0,"__isset":{"ParentToConstraint":false,"TranslationalVelocity":false,"RotationalVelocity":false,"WeightingFactor":false}},"AccelerationConstraint":{"ParentObjectID":"","ParentToConstraint":{"ID":"","Position":{"X":0,"Y":0,"Z":0},"Rotation":{"X":0,"Y":0,"Z":0,"W":0},"Parent":"","__isset":{"Parent":false}},"TranslationalAcceleration":{"X":0,"Y":0,"Z":0},"RotationalAcceleration":{"X":0,"Y":0,"Z":0},"WeightingFactor":0,"__isset":{"ParentToConstraint":false,"TranslationalAcceleration":false,"RotationalAcceleration":false,"WeightingFactor":false}},"__isset":{"GeometryConstraint":true,"VelocityConstraint":false,"AccelerationConstraint":false}},{"JointType":"RightThumbMid","GeometryConstraint":{"ParentObjectID":"","ParentToConstraint":{"ID":"147605a3-9c80-49c7-8cbd-5368aa2ce532","Position":{"X":-1.1175872316471214E-7,"Y":0.04397115111351013,"Z":0.028201885521411896},"Rotation":{"X":0.3490336537361145,"Y":0.1569145768880844,"Z":-0.37882494926452637,"W":0.8426417112350464},"Parent":"","__isset":{"Parent":false}},"TranslationConstraint":{"Type":"BOX","Limits":{"X":{"Min":0,"Max":0},"Y":{"Min":0,"Max":0},"Z":{"Min":0,"Max":0}}},"RotationConstraint":{"Limits":{"X":{"Min":0,"Max":0},"Y":{"Min":0,"Max":0},"Z":{"Min":0,"Max":0}}},"WeightingFactor":0,"__isset":{"ParentToConstraint":true,"TranslationConstraint":false,"RotationConstraint":false,"WeightingFactor":false}},"VelocityConstraint":{"ParentObjectID":"","ParentToConstraint":{"ID":"","Position":{"X":0,"Y":0,"Z":0},"Rotation":{"X":0,"Y":0,"Z":0,"W":0},"Parent":"","__isset":{"Parent":false}},"TranslationalVelocity":{"X":0,"Y":0,"Z":0},"RotationalVelocity":{"X":0,"Y":0,"Z":0},"WeightingFactor":0,"__isset":{"ParentToConstraint":false,"TranslationalVelocity":false,"RotationalVelocity":false,"WeightingFactor":false}},"AccelerationConstraint":{"ParentObjectID":"","ParentToConstraint":{"ID":"","Position":{"X":0,"Y":0,"Z":0},"Rotation":{"X":0,"Y":0,"Z":0,"W":0},"Parent":"","__isset":{"Parent":false}},"TranslationalAcceleration":{"X":0,"Y":0,"Z":0},"RotationalAcceleration":{"X":0,"Y":0,"Z":0},"WeightingFactor":0,"__isset":{"ParentToConstraint":false,"TranslationalAcceleration":false,"RotationalAcceleration":false,"WeightingFactor":false}},"__isset":{"GeometryConstraint":true,"VelocityConstraint":false,"AccelerationConstraint":false}},{"JointType":"RightThumbMeta","GeometryConstraint":{"ParentObjectID":"","ParentToConstraint":{"ID":"3e6e72ed-cd87-49f3-bea3-211e62a81912","Position":{"X":0,"Y":0.035892121493816376,"Z":0},"Rotation":{"X":0,"Y":0,"Z":0,"W":1},"Parent":"","__isset":{"Parent":false}},"TranslationConstraint":{"Type":"BOX","Limits":{"X":{"Min":0,"Max":0},"Y":{"Min":0,"Max":0},"Z":{"Min":0,"Max":0}}},"RotationConstraint":{"Limits":{"X":{"Min":0,"Max":0},"Y":{"Min":0,"Max":0},"Z":{"Min":0,"Max":0}}},"WeightingFactor":0,"__isset":{"ParentToConstraint":true,"TranslationConstraint":false,"RotationConstraint":false,"WeightingFactor":false}},"VelocityConstraint":{"ParentObjectID":"","ParentToConstraint":{"ID":"","Position":{"X":0,"Y":0,"Z":0},"Rotation":{"X":0,"Y":0,"Z":0,"W":0},"Parent":"","__isset":{"Parent":false}},"TranslationalVelocity":{"X":0,"Y":0,"Z":0},"RotationalVelocity":{"X":0,"Y":0,"Z":0},"WeightingFactor":0,"__isset":{"ParentToConstraint":false,"TranslationalVelocity":false,"RotationalVelocity":false,"WeightingFactor":false}},"AccelerationConstraint":{"ParentObjectID":"","ParentToConstraint":{"ID":"","Position":{"X":0,"Y":0,"Z":0},"Rotation":{"X":0,"Y":0,"Z":0,"W":0},"Parent":"","__isset":{"Parent":false}},"TranslationalAcceleration":{"X":0,"Y":0,"Z":0},"RotationalAcceleration":{"X":0,"Y":0,"Z":0},"WeightingFactor":0,"__isset":{"ParentToConstraint":false,"TranslationalAcceleration":false,"RotationalAcceleration":false,"WeightingFactor":false}},"__isset":{"GeometryConstraint":true,"VelocityConstraint":false,"AccelerationConstraint":false}},{"JointType":"RightThumbCarpal","GeometryConstraint":{"ParentObjectID":"","ParentToConstraint":{"ID":"f0bfc840-954c-4a46-b473-dd4a951f6bd3","Position":{"X":0,"Y":0.04247378185391426,"Z":0},"Rotation":{"X":0,"Y":0,"Z":0,"W":1},"Parent":"","__isset":{"Parent":false}},"TranslationConstraint":{"Type":"BOX","Limits":{"X":{"Min":0,"Max":0},"Y":{"Min":0,"Max":0},"Z":{"Min":0,"Max":0}}},"RotationConstraint":{"Limits":{"X":{"Min":0,"Max":0},"Y":{"Min":0,"Max":0},"Z":{"Min":0,"Max":0}}},"WeightingFactor":0,"__isset":{"ParentToConstraint":true,"TranslationConstraint":false,"RotationConstraint":false,"WeightingFactor":false}},"VelocityConstraint":{"ParentObjectID":"","ParentToConstraint":{"ID":"","Position":{"X":0,"Y":0,"Z":0},"Rotation":{"X":0,"Y":0,"Z":0,"W":0},"Parent":"","__isset":{"Parent":false}},"TranslationalVelocity":{"X":0,"Y":0,"Z":0},"RotationalVelocity":{"X":0,"Y":0,"Z":0},"WeightingFactor":0,"__isset":{"ParentToConstraint":false,"TranslationalVelocity":false,"RotationalVelocity":false,"WeightingFactor":false}},"AccelerationConstraint":{"ParentObjectID":"","ParentToConstraint":{"ID":"","Position":{"X":0,"Y":0,"Z":0},"Rotation":{"X":0,"Y":0,"Z":0,"W":0},"Parent":"","__isset":{"Parent":false}},"TranslationalAcceleration":{"X":0,"Y":0,"Z":0},"RotationalAcceleration":{"X":0,"Y":0,"Z":0},"WeightingFactor":0,"__isset":{"ParentToConstraint":false,"TranslationalAcceleration":false,"RotationalAcceleration":false,"WeightingFactor":false}},"__isset":{"GeometryConstraint":true,"VelocityConstraint":false,"AccelerationConstraint":false}},{"JointType":"RightThumbTip","GeometryConstraint":{"ParentObjectID":"","ParentToConstraint":{"ID":"158c129d-ba31-4429-8759-cefd17eb1a1d","Position":{"X":0,"Y":0.029999999329447746,"Z":0},"Rotation":{"X":0,"Y":0,"Z":0,"W":1},"Parent":"","__isset":{"Parent":false}},"TranslationConstraint":{"Type":"BOX","Limits":{"X":{"Min":0,"Max":0},"Y":{"Min":0,"Max":0},"Z":{"Min":0,"Max":0}}},"RotationConstraint":{"Limits":{"X":{"Min":0,"Max":0},"Y":{"Min":0,"Max":0},"Z":{"Min":0,"Max":0}}},"WeightingFactor":0,"__isset":{"ParentToConstraint":true,"TranslationConstraint":false,"RotationConstraint":false,"WeightingFactor":false}},"VelocityConstraint":{"ParentObjectID":"","ParentToConstraint":{"ID":"","Position":{"X":0,"Y":0,"Z":0},"Rotation":{"X":0,"Y":0,"Z":0,"W":0},"Parent":"","__isset":{"Parent":false}},"TranslationalVelocity":{"X":0,"Y":0,"Z":0},"RotationalVelocity":{"X":0,"Y":0,"Z":0},"WeightingFactor":0,"__isset":{"ParentToConstraint":false,"TranslationalVelocity":false,"RotationalVelocity":false,"WeightingFactor":false}},"AccelerationConstraint":{"ParentObjectID":"","ParentToConstraint":{"ID":"","Position":{"X":0,"Y":0,"Z":0},"Rotation":{"X":0,"Y":0,"Z":0,"W":0},"Parent":"","__isset":{"Parent":false}},"TranslationalAcceleration":{"X":0,"Y":0,"Z":0},"RotationalAcceleration":{"X":0,"Y":0,"Z":0},"WeightingFactor":0,"__isset":{"ParentToConstraint":false,"TranslationalAcceleration":false,"RotationalAcceleration":false,"WeightingFactor":false}},"__isset":{"GeometryConstraint":true,"VelocityConstraint":false,"AccelerationConstraint":false}}],"__isset":{"JointConstraints":true}},"JointConstraint":{"JointType":"Undefined","GeometryConstraint":{"ParentObjectID":"","ParentToConstraint":{"ID":"","Position":{"X":0,"Y":0,"Z":0},"Rotation":{"X":0,"Y":0,"Z":0,"W":0},"Parent":"","__isset":{"Parent":false}},"TranslationConstraint":{"Type":"BOX","Limits":{"X":{"Min":0,"Max":0},"Y":{"Min":0,"Max":0},"Z":{"Min":0,"Max":0}}},"RotationConstraint":{"Limits":{"X":{"Min":0,"Max":0},"Y":{"Min":0,"Max":0},"Z":{"Min":0,"Max":0}}},"WeightingFactor":0,"__isset":{"ParentToConstraint":false,"TranslationConstraint":false,"RotationConstraint":false,"WeightingFactor":false}},"VelocityConstraint":{"ParentObjectID":"","ParentToConstraint":{"ID":"","Position":{"X":0,"Y":0,"Z":0},"Rotation":{"X":0,"Y":0,"Z":0,"W":0},"Parent":"","__isset":{"Parent":false}},"TranslationalVelocity":{"X":0,"Y":0,"Z":0},"RotationalVelocity":{"X":0,"Y":0,"Z":0},"WeightingFactor":0,"__isset":{"ParentToConstraint":false,"TranslationalVelocity":false,"RotationalVelocity":false,"WeightingFactor":false}},"AccelerationConstraint":{"ParentObjectID":"","ParentToConstraint":{"ID":"","Position":{"X":0,"Y":0,"Z":0},"Rotation":{"X":0,"Y":0,"Z":0,"W":0},"Parent":"","__isset":{"Parent":false}},"TranslationalAcceleration":{"X":0,"Y":0,"Z":0},"RotationalAcceleration":{"X":0,"Y":0,"Z":0},"WeightingFactor":0,"__isset":{"ParentToConstraint":false,"TranslationalAcceleration":false,"RotationalAcceleration":false,"WeightingFactor":false}},"__isset":{"GeometryConstraint":false,"VelocityConstraint":false,"AccelerationConstraint":false}},"Properties":null,"__isset":{"GeometryConstraint":false,"VelocityConstraint":false,"AccelerationConstraint":false,"PathConstraint":false,"JointPathConstraint":false,"PostureConstraint":true,"JointConstraint":false,"Properties":false}},{"ID":"Posture constraint","GeometryConstraint":null,"VelocityConstraint":null,"AccelerationConstraint":null,"PathConstraint":null,"JointPathConstraint":null,"PostureConstraint":{"Posture":{"AvatarID":"","PostureData":[],"PartialJointList":null,"__isset":{"PartialJointList":false}},"JointConstraints":[{"JointType":"RightWrist","GeometryConstraint":{"ParentObjectID":"","ParentToConstraint":{"ID":"9d90533b-8bca-43c8-bf4a-53429f43db0f","Position":{"X":0.06809999793767929,"Y":0.9466000199317932,"Z":0.5289999842643738},"Rotation":{"X":0.0877721756696701,"Y":-0.7122747898101807,"Z":-0.695723295211792,"W":-0.030495429411530495},"Parent":null,"__isset":{"Parent":false}},"TranslationConstraint":null,"RotationConstraint":null,"WeightingFactor":0,"__isset":{"ParentToConstraint":true,"TranslationConstraint":false,"RotationConstraint":false,"WeightingFactor":false}},"VelocityConstraint":null,"AccelerationConstraint":null,"__isset":{"GeometryConstraint":true,"VelocityConstraint":false,"AccelerationConstraint":false}},{"JointType":"RightMiddleProximal","GeometryConstraint":{"ParentObjectID":"","ParentToConstraint":{"ID":"e0d3ce37-51d9-4d7f-93df-72edf4fbd662","Position":{"X":-1.1920928955078125E-7,"Y":0.11821141839027405,"Z":5.960468740795477E-8},"Rotation":{"X":3.7252898543727042E-9,"Y":4.738102887813511E-8,"Z":-0.32847949862480164,"W":0.9445111751556396},"Parent":null,"__isset":{"Parent":false}},"TranslationConstraint":null,"RotationConstraint":null,"WeightingFactor":0,"__isset":{"ParentToConstraint":true,"TranslationConstraint":false,"RotationConstraint":false,"WeightingFactor":false}},"VelocityConstraint":null,"AccelerationConstraint":null,"__isset":{"GeometryConstraint":true,"VelocityConstraint":false,"AccelerationConstraint":false}},{"JointType":"RightMiddleMeta","GeometryConstraint":{"ParentObjectID":"","ParentToConstraint":{"ID":"92e54b7e-5ce8-46d3-b94d-cbddce587584","Position":{"X":0,"Y":0.03957550227642059,"Z":0},"Rotation":{"X":-2.5678856374611314E-8,"Y":2.5543320347765075E-8,"Z":-0.36731332540512085,"W":0.9300972819328308},"Parent":null,"__isset":{"Parent":false}},"TranslationConstraint":null,"RotationConstraint":null,"WeightingFactor":0,"__isset":{"ParentToConstraint":true,"TranslationConstraint":false,"RotationConstraint":false,"WeightingFactor":false}},"VelocityConstraint":null,"AccelerationConstraint":null,"__isset":{"GeometryConstraint":true,"VelocityConstraint":false,"AccelerationConstraint":false}},{"JointType":"RightMiddleDistal","GeometryConstraint":{"ParentObjectID":"","ParentToConstraint":{"ID":"68e23e1a-0669-43c1-a071-dec7f554ccef","Position":{"X":0,"Y":0.031451690942049026,"Z":0},"Rotation":{"X":0,"Y":0,"Z":0,"W":1},"Parent":null,"__isset":{"Parent":false}},"TranslationConstraint":null,"RotationConstraint":null,"WeightingFactor":0,"__isset":{"ParentToConstraint":true,"TranslationConstraint":false,"RotationConstraint":false,"WeightingFactor":false}},"VelocityConstraint":null,"AccelerationConstraint":null,"__isset":{"GeometryConstraint":true,"VelocityConstraint":false,"AccelerationConstraint":false}},{"JointType":"RightMiddleTip","GeometryConstraint":{"ParentObjectID":"","ParentToConstraint":{"ID":"81188fdd-1eb1-4606-bdc8-f52a138c1f2b","Position":{"X":0,"Y":0.029999999329447746,"Z":0},"Rotation":{"X":0,"Y":0,"Z":0,"W":1},"Parent":null,"__isset":{"Parent":false}},"TranslationConstraint":null,"RotationConstraint":null,"WeightingFactor":0,"__isset":{"ParentToConstraint":true,"TranslationConstraint":false,"RotationConstraint":false,"WeightingFactor":false}},"VelocityConstraint":null,"AccelerationConstraint":null,"__isset":{"GeometryConstraint":true,"VelocityConstraint":false,"AccelerationConstraint":false}},{"JointType":"RightIndexProximal","GeometryConstraint":{"ParentObjectID":"","ParentToConstraint":{"ID":"90bb3b56-90da-47f8-8d54-d641083feb0c","Position":{"X":-1.1175872316471214E-7,"Y":0.1199701726436615,"Z":0.02809811383485794},"Rotation":{"X":3.7252898543727042E-9,"Y":4.738102887813511E-8,"Z":-0.32847949862480164,"W":0.9445111751556396},"Parent":null,"__isset":{"Parent":false}},"TranslationConstraint":null,"RotationConstraint":null,"WeightingFactor":0,"__isset":{"ParentToConstraint":true,"TranslationConstraint":false,"RotationConstraint":false,"WeightingFactor":false}},"VelocityConstraint":null,"AccelerationConstraint":null,"__isset":{"GeometryConstraint":true,"VelocityConstraint":false,"AccelerationConstraint":false}},{"JointType":"RightIndexMeta","GeometryConstraint":{"ParentObjectID":"","ParentToConstraint":{"ID":"ae612e73-6025-42bd-9470-f2b4d53a1fe8","Position":{"X":0,"Y":0.030107565224170685,"Z":0},"Rotation":{"X":-2.5678856374611314E-8,"Y":2.5543320347765075E-8,"Z":-0.36731332540512085,"W":0.9300972819328308},"Parent":null,"__isset":{"Parent":false}},"TranslationConstraint":null,"RotationConstraint":null,"WeightingFactor":0,"__isset":{"ParentToConstraint":true,"TranslationConstraint":false,"RotationConstraint":false,"WeightingFactor":false}},"VelocityConstraint":null,"AccelerationConstraint":null,"__isset":{"GeometryConstraint":true,"VelocityConstraint":false,"AccelerationConstraint":false}},{"JointType":"RightIndexDistal","GeometryConstraint":{"ParentObjectID":"","ParentToConstraint":{"ID":"52402784-9fc1-4568-8bb4-ba247441779a","Position":{"X":0,"Y":0.02719544805586338,"Z":0},"Rotation":{"X":0,"Y":0,"Z":0,"W":1},"Parent":null,"__isset":{"Parent":false}},"TranslationConstraint":null,"RotationConstraint":null,"WeightingFactor":0,"__isset":{"ParentToConstraint":true,"TranslationConstraint":false,"RotationConstraint":false,"WeightingFactor":false}},"VelocityConstraint":null,"AccelerationConstraint":null,"__isset":{"GeometryConstraint":true,"VelocityConstraint":false,"AccelerationConstraint":false}},{"JointType":"RightIndexTip","GeometryConstraint":{"ParentObjectID":"","ParentToConstraint":{"ID":"e228f899-7b32-440d-aefd-ff1d13eeb61f","Position":{"X":0,"Y":0.029999999329447746,"Z":0},"Rotation":{"X":0,"Y":0,"Z":0,"W":1},"Parent":null,"__isset":{"Parent":false}},"TranslationConstraint":null,"RotationConstraint":null,"WeightingFactor":0,"__isset":{"ParentToConstraint":true,"TranslationConstraint":false,"RotationConstraint":false,"WeightingFactor":false}},"VelocityConstraint":null,"AccelerationConstraint":null,"__isset":{"GeometryConstraint":true,"VelocityConstraint":false,"AccelerationConstraint":false}},{"JointType":"RightRingProximal","GeometryConstraint":{"ParentObjectID":"","ParentToConstraint":{"ID":"2294b102-ab3c-417c-b4a4-8879ad1ce89e","Position":{"X":-1.2293459406009788E-7,"Y":0.11081787943840027,"Z":-0.022562745958566666},"Rotation":{"X":3.7252898543727042E-9,"Y":4.738102887813511E-8,"Z":-0.32847949862480164,"W":0.9445111751556396},"Parent":null,"__isset":{"Parent":false}},"TranslationConstraint":null,"RotationConstraint":null,"WeightingFactor":0,"__isset":{"ParentToConstraint":true,"TranslationConstraint":false,"RotationConstraint":false,"WeightingFactor":false}},"VelocityConstraint":null,"AccelerationConstraint":null,"__isset":{"GeometryConstraint":true,"VelocityConstraint":false,"AccelerationConstraint":false}},{"JointType":"RightRingMeta","GeometryConstraint":{"ParentObjectID":"","ParentToConstraint":{"ID":"13d9320f-b9e4-4ec7-8c48-892c53771125","Position":{"X":0,"Y":0.03474121913313866,"Z":0},"Rotation":{"X":-2.5678856374611314E-8,"Y":2.5543320347765075E-8,"Z":-0.36731332540512085,"W":0.9300972819328308},"Parent":null,"__isset":{"Parent":false}},"TranslationConstraint":null,"RotationConstraint":null,"WeightingFactor":0,"__isset":{"ParentToConstraint":true,"TranslationConstraint":false,"RotationConstraint":false,"WeightingFactor":false}},"VelocityConstraint":null,"AccelerationConstraint":null,"__isset":{"GeometryConstraint":true,"VelocityConstraint":false,"AccelerationConstraint":false}},{"JointType":"RightRingDistal","GeometryConstraint":{"ParentObjectID":"","ParentToConstraint":{"ID":"c7d82108-1344-46da-a34d-190225c4370d","Position":{"X":0,"Y":0.02874886617064476,"Z":0},"Rotation":{"X":0,"Y":0,"Z":0,"W":1},"Parent":null,"__isset":{"Parent":false}},"TranslationConstraint":null,"RotationConstraint":null,"WeightingFactor":0,"__isset":{"ParentToConstraint":true,"TranslationConstraint":false,"RotationConstraint":false,"WeightingFactor":false}},"VelocityConstraint":null,"AccelerationConstraint":null,"__isset":{"GeometryConstraint":true,"VelocityConstraint":false,"AccelerationConstraint":false}},{"JointType":"RightRingTip","GeometryConstraint":{"ParentObjectID":"","ParentToConstraint":{"ID":"c1487abd-ef14-41ea-93fb-69bd49fac025","Position":{"X":0,"Y":0.029999999329447746,"Z":0},"Rotation":{"X":0,"Y":0,"Z":0,"W":1},"Parent":null,"__isset":{"Parent":false}},"TranslationConstraint":null,"RotationConstraint":null,"WeightingFactor":0,"__isset":{"ParentToConstraint":true,"TranslationConstraint":false,"RotationConstraint":false,"WeightingFactor":false}},"VelocityConstraint":null,"AccelerationConstraint":null,"__isset":{"GeometryConstraint":true,"VelocityConstraint":false,"AccelerationConstraint":false}},{"JointType":"RightLittleProximal","GeometryConstraint":{"ParentObjectID":"","ParentToConstraint":{"ID":"1e14e09d-7f05-4d4d-8613-c800e1a1f08c","Position":{"X":-1.266598843585598E-7,"Y":0.10160025954246521,"Z":-0.041280217468738556},"Rotation":{"X":3.7252898543727042E-9,"Y":4.738102887813511E-8,"Z":-0.32847949862480164,"W":0.9445111751556396},"Parent":null,"__isset":{"Parent":false}},"TranslationConstraint":null,"RotationConstraint":null,"WeightingFactor":0,"__isset":{"ParentToConstraint":true,"TranslationConstraint":false,"RotationConstraint":false,"WeightingFactor":false}},"VelocityConstraint":null,"AccelerationConstraint":null,"__isset":{"GeometryConstraint":true,"VelocityConstraint":false,"AccelerationConstraint":false}},{"JointType":"RightLittleMeta","GeometryConstraint":{"ParentObjectID":"","ParentToConstraint":{"ID":"24fcc614-0117-4fcb-93e1-d235b97c224f","Position":{"X":0,"Y":0.02462206967175007,"Z":0},"Rotation":{"X":-2.5678856374611314E-8,"Y":2.5543320347765075E-8,"Z":-0.36731332540512085,"W":0.9300972819328308},"Parent":null,"__isset":{"Parent":false}},"TranslationConstraint":null,"RotationConstraint":null,"WeightingFactor":0,"__isset":{"ParentToConstraint":true,"TranslationConstraint":false,"RotationConstraint":false,"WeightingFactor":false}},"VelocityConstraint":null,"AccelerationConstraint":null,"__isset":{"GeometryConstraint":true,"VelocityConstraint":false,"AccelerationConstraint":false}},{"JointType":"RightLittleDistal","GeometryConstraint":{"ParentObjectID":"","ParentToConstraint":{"ID":"e8af99f3-0478-4f25-b9a2-74b028d950cd","Position":{"X":0,"Y":0.018097683787345886,"Z":0},"Rotation":{"X":0,"Y":0,"Z":0,"W":1},"Parent":null,"__isset":{"Parent":false}},"TranslationConstraint":null,"RotationConstraint":null,"WeightingFactor":0,"__isset":{"ParentToConstraint":true,"TranslationConstraint":false,"RotationConstraint":false,"WeightingFactor":false}},"VelocityConstraint":null,"AccelerationConstraint":null,"__isset":{"GeometryConstraint":true,"VelocityConstraint":false,"AccelerationConstraint":false}},{"JointType":"RightLittleTip","GeometryConstraint":{"ParentObjectID":"","ParentToConstraint":{"ID":"a1b7289b-938a-4bff-bd01-39880261f7b0","Position":{"X":0,"Y":0.029999999329447746,"Z":0},"Rotation":{"X":0,"Y":0,"Z":0,"W":1},"Parent":null,"__isset":{"Parent":false}},"TranslationConstraint":null,"RotationConstraint":null,"WeightingFactor":0,"__isset":{"ParentToConstraint":true,"TranslationConstraint":false,"RotationConstraint":false,"WeightingFactor":false}},"VelocityConstraint":null,"AccelerationConstraint":null,"__isset":{"GeometryConstraint":true,"VelocityConstraint":false,"AccelerationConstraint":false}},{"JointType":"RightThumbMid","GeometryConstraint":{"ParentObjectID":"","ParentToConstraint":{"ID":"9aa94d6a-31a0-431a-a7ca-438ec5a4cbf0","Position":{"X":-1.1175872316471214E-7,"Y":0.04397115111351013,"Z":0.028201885521411896},"Rotation":{"X":0.3490336537361145,"Y":0.1569145768880844,"Z":-0.37882494926452637,"W":0.8426417112350464},"Parent":null,"__isset":{"Parent":false}},"TranslationConstraint":null,"RotationConstraint":null,"WeightingFactor":0,"__isset":{"ParentToConstraint":true,"TranslationConstraint":false,"RotationConstraint":false,"WeightingFactor":false}},"VelocityConstraint":null,"AccelerationConstraint":null,"__isset":{"GeometryConstraint":true,"VelocityConstraint":false,"AccelerationConstraint":false}},{"JointType":"RightThumbMeta","GeometryConstraint":{"ParentObjectID":"","ParentToConstraint":{"ID":"47975a75-2c79-457f-a55f-c4e4cd5fd964","Position":{"X":0,"Y":0.035892121493816376,"Z":0},"Rotation":{"X":0,"Y":0,"Z":0,"W":1},"Parent":null,"__isset":{"Parent":false}},"TranslationConstraint":null,"RotationConstraint":null,"WeightingFactor":0,"__isset":{"ParentToConstraint":true,"TranslationConstraint":false,"RotationConstraint":false,"WeightingFactor":false}},"VelocityConstraint":null,"AccelerationConstraint":null,"__isset":{"GeometryConstraint":true,"VelocityConstraint":false,"AccelerationConstraint":false}},{"JointType":"RightThumbCarpal","GeometryConstraint":{"ParentObjectID":"","ParentToConstraint":{"ID":"c6fd580d-16f5-4edd-8cd8-2229b905f65d","Position":{"X":0,"Y":0.04247378185391426,"Z":0},"Rotation":{"X":0,"Y":0,"Z":0,"W":1},"Parent":null,"__isset":{"Parent":false}},"TranslationConstraint":null,"RotationConstraint":null,"WeightingFactor":0,"__isset":{"ParentToConstraint":true,"TranslationConstraint":false,"RotationConstraint":false,"WeightingFactor":false}},"VelocityConstraint":null,"AccelerationConstraint":null,"__isset":{"GeometryConstraint":true,"VelocityConstraint":false,"AccelerationConstraint":false}},{"JointType":"RightThumbTip","GeometryConstraint":{"ParentObjectID":"","ParentToConstraint":{"ID":"5d5e0ef7-8873-4582-b34e-0e6f170c54b5","Position":{"X":0,"Y":0.029999999329447746,"Z":0},"Rotation":{"X":0,"Y":0,"Z":0,"W":1},"Parent":null,"__isset":{"Parent":false}},"TranslationConstraint":null,"RotationConstraint":null,"WeightingFactor":0,"__isset":{"ParentToConstraint":true,"TranslationConstraint":false,"RotationConstraint":false,"WeightingFactor":false}},"VelocityConstraint":null,"AccelerationConstraint":null,"__isset":{"GeometryConstraint":true,"VelocityConstraint":false,"AccelerationConstraint":false}}],"__isset":{"JointConstraints":true}},"JointConstraint":null,"Properties":null,"__isset":{"GeometryConstraint":false,"VelocityConstraint":false,"AccelerationConstraint":false,"PathConstraint":false,"JointPathConstraint":false,"PostureConstraint":true,"JointConstraint":false,"Properties":false}}]